[{"first_name": "Ralf", "last_name": "F\u00e4hrmann", "price": 3065250.0, "expiration": "2023-05-22T04:13:54.698550+02:00", "team_id": "8", "position": "TW", "trend": 1}, {"first_name": "Kevin", "last_name": "Vogt", "price": 500000.0, "expiration": "2023-05-22T08:26:06.698582+02:00", "team_id": "14", "position": "ABW", "trend": 0}, {"first_name": "Patrick", "last_name": "Herrmann", "price": 500000.0, "expiration": "2023-05-22T04:02:23.698595+02:00", "team_id": "15", "position": "MF", "trend": 0}, {"first_name": "Jonathan", "last_name": "Schmid", "price": 500000.0, "expiration": "2023-05-23T00:19:28.698607+02:00", "team_id": "5", "position": "ABW", "trend": 0}, {"first_name": "Konstantinos", "last_name": "Stafylidis", "price": 500000.0, "expiration": "2023-05-22T04:04:33.698616+02:00", "team_id": "24", "position": "ABW", "trend": 0}, {"first_name": "Pavel", "last_name": "Kader\u00e1bek", "price": 1584259.0, "expiration": "2023-05-22T02:59:53.698626+02:00", "team_id": "14", "position": "ABW", "trend": 2}, {"first_name": "Florian", "last_name": "M\u00fcller", "price": 500000.0, "expiration": "2023-05-23T02:26:35.698637+02:00", "team_id": "9", "position": "TW", "trend": 0}, {"first_name": "Niklas", "last_name": "Dorsch", "price": 500000.0, "expiration": "2023-05-22T01:48:18.698647+02:00", "team_id": "13", "position": "MF", "trend": 0}, {"first_name": "Takuma", "last_name": "Asano", "price": 963143.0, "expiration": "2023-05-22T16:26:54.698657+02:00", "team_id": "24", "position": "MF", "trend": 1}, {"first_name": "Finn", "last_name": "Dahmen", "price": 517972.0, "expiration": "2023-05-22T05:43:53.698667+02:00", "team_id": "18", "position": "TW", "trend": 1}, {"first_name": "Leandro", "last_name": "Barreiro Martins", "price": 5718026.0, "expiration": "2023-05-23T08:38:45.698677+02:00", "team_id": "18", "position": "MF", "trend": 2}, {"first_name": "Paulo", "last_name": "Ot\u00e1vio", "price": 6142468.0, "expiration": "2023-05-22T00:48:52.698687+02:00", "team_id": "11", "position": "ABW", "trend": 2}, {"first_name": "Christopher", "last_name": "Antwi-Adjei", "price": 1172696.0, "expiration": "2023-05-22T16:34:53.698696+02:00", "team_id": "24", "position": "MF", "trend": 2}, {"first_name": "Iago Amaral", "last_name": "Borduchi", "price": 500000.0, "expiration": "2023-05-22T04:33:47.698706+02:00", "team_id": "13", "position": "ABW", "trend": 0}, {"first_name": "Omar", "last_name": "Marmoush", "price": 2981759.0, "expiration": "2023-05-22T03:26:42.698716+02:00", "team_id": "11", "position": "ANG", "trend": 2}, {"first_name": "Stevan", "last_name": "Joveti\u0107", "price": 732358.0, "expiration": "2023-05-22T04:03:13.698729+02:00", "team_id": "20", "position": "ANG", "trend": 2}, {"first_name": "Kevin", "last_name": "Paredes", "price": 500000.0, "expiration": "2023-05-22T03:36:36.698739+02:00", "team_id": "11", "position": "MF", "trend": 0}, {"first_name": "Tjark", "last_name": "Ernst", "price": 500000.0, "expiration": "2023-05-23T12:01:49.698749+02:00", "team_id": "20", "position": "TW", "trend": 0}, {"first_name": "Kasper", "last_name": "Dolberg", "price": 500000.0, "expiration": "2023-05-22T21:02:42.698759+02:00", "team_id": "14", "position": "ANG", "trend": 0}, {"first_name": "Arne", "last_name": "Engels", "price": 1202398.0, "expiration": "2023-05-23T07:31:42.698768+02:00", "team_id": "13", "position": "MF", "trend": 2}, {"first_name": "Jere", "last_name": "Uronen", "price": 500000.0, "expiration": "2023-05-23T10:15:23.698777+02:00", "team_id": "8", "position": "ABW", "trend": 0}, {"first_name": "Renato", "last_name": "De Palma Veiga", "price": 500000.0, "expiration": "2023-05-23T19:26:53.286789+02:00", "team_id": "13", "position": "MF", "trend": 0}]