[{"first_name": "Janis", "last_name": "Blaswich", "price": 7224487.0, "expiration": "2022-12-12T11:34:26.800615+01:00", "team_id": "43", "position": "TW", "trend": 2}, {"first_name": "Kenan", "last_name": "Karaman", "price": 1109410.0, "expiration": "2022-12-13T08:16:28.800663+01:00", "team_id": "8", "position": "ANG", "trend": 2}, {"first_name": "Anthony", "last_name": "Modeste", "price": 6973312.0, "expiration": "2022-12-13T04:30:08.800694+01:00", "team_id": "3", "position": "ANG", "trend": 2}, {"first_name": "Ihlas", "last_name": "Bebou", "price": 3061003.0, "expiration": "2022-12-13T19:49:07.208370+01:00", "team_id": "14", "position": "ANG", "trend": 1}, {"first_name": "Mamadou", "last_name": "Doucour\u00e9", "price": 500000.0, "expiration": "2022-12-12T21:52:36.208413+01:00", "team_id": "15", "position": "ABW", "trend": 0}, {"first_name": "Emil", "last_name": "Forsberg", "price": 9450526.0, "expiration": "2022-12-12T15:47:44.208428+01:00", "team_id": "43", "position": "MF", "trend": 2}, {"first_name": "Alexander", "last_name": "Meyer", "price": 2109679.0, "expiration": "2022-12-12T16:03:24.208442+01:00", "team_id": "3", "position": "TW", "trend": 1}, {"first_name": "Chris", "last_name": "F\u00fchrich", "price": 3568395.0, "expiration": "2022-12-13T07:30:56.208453+01:00", "team_id": "9", "position": "MF", "trend": 2}, {"first_name": "Paul", "last_name": "Jaeckel", "price": 3318718.0, "expiration": "2022-12-13T05:32:21.208464+01:00", "team_id": "40", "position": "ABW", "trend": 2}, {"first_name": "Jean-Paul", "last_name": "Bo\u00ebtius", "price": 2331539.0, "expiration": "2022-12-13T01:47:41.208476+01:00", "team_id": "20", "position": "MF", "trend": 2}, {"first_name": "Jakob", "last_name": "Busk", "price": 500000.0, "expiration": "2022-12-12T13:19:00.613291+01:00", "team_id": "40", "position": "TW", "trend": 0}, {"first_name": "Sebastian", "last_name": "Andersson", "price": 500000.0, "expiration": "2022-12-12T19:09:43.006303+01:00", "team_id": "28", "position": "ANG", "trend": 0}, {"first_name": "Tobias", "last_name": "Mohr", "price": 3989670.0, "expiration": "2022-12-13T15:03:04.006348+01:00", "team_id": "8", "position": "MF", "trend": 2}, {"first_name": "Marcus", "last_name": "Ingvartsen", "price": 3661916.0, "expiration": "2022-12-12T18:45:13.006363+01:00", "team_id": "18", "position": "MF", "trend": 2}, {"first_name": "Jan Jakob", "last_name": "Olschowsky", "price": 6339198.0, "expiration": "2022-12-12T14:43:38.406912+01:00", "team_id": "15", "position": "TW", "trend": 1}, {"first_name": "Naouirou", "last_name": "Ahamada", "price": 4885061.0, "expiration": "2022-12-13T11:31:42.406951+01:00", "team_id": "9", "position": "MF", "trend": 2}, {"first_name": "Kevin", "last_name": "Schade", "price": 1374141.0, "expiration": "2022-12-13T09:31:41.406965+01:00", "team_id": "5", "position": "MF", "trend": 2}, {"first_name": "Kiliann", "last_name": "Sildillia", "price": 8680590.0, "expiration": "2022-12-12T18:55:08.406977+01:00", "team_id": "5", "position": "ABW", "trend": 2}, {"first_name": "Marcel Laurenz", "last_name": "Lotka", "price": 500000.0, "expiration": "2022-12-12T12:58:07.406987+01:00", "team_id": "3", "position": "TW", "trend": 0}, {"first_name": "Tjark", "last_name": "Ernst", "price": 500000.0, "expiration": "2022-12-13T20:20:13.407001+01:00", "team_id": "20", "position": "TW", "trend": 0}, {"first_name": "Bartol", "last_name": "Franjic", "price": 3387135.0, "expiration": "2022-12-14T00:06:13.803705+01:00", "team_id": "11", "position": "MF", "trend": 1}, {"first_name": "Nathan", "last_name": "Ngoumou", "price": 5614693.0, "expiration": "2022-12-12T14:47:42.204739+01:00", "team_id": "15", "position": "MF", "trend": 1}]