[{"first_name": "Kevin", "last_name": "Akpoguma", "price": 3825901.0, "expiration": "2023-01-29T02:50:10.498148+01:00", "team_id": "14", "position": "ABW", "trend": 2}, {"first_name": "Niklas", "last_name": "Stark", "price": 4453118.0, "expiration": "2023-01-28T22:39:40.498174+01:00", "team_id": "10", "position": "ABW", "trend": 1}, {"first_name": "Oliver", "last_name": "Baumann", "price": 10671077.0, "expiration": "2023-01-29T07:53:18.498185+01:00", "team_id": "14", "position": "TW", "trend": 1}, {"first_name": "Dominick", "last_name": "Drexler", "price": 1702117.0, "expiration": "2023-01-29T11:51:31.498194+01:00", "team_id": "8", "position": "MF", "trend": 2}, {"first_name": "John Anthony", "last_name": "Brooks", "price": 4839475.0, "expiration": "2023-01-28T22:43:01.080223+01:00", "team_id": "14", "position": "ABW", "trend": 2}, {"first_name": "Davie", "last_name": "Selke", "price": 7365427.0, "expiration": "2023-01-30T00:30:44.080260+01:00", "team_id": "28", "position": "ANG", "trend": 2}, {"first_name": "Pierre", "last_name": "Kunde", "price": 6363577.0, "expiration": "2023-01-29T12:55:40.669528+01:00", "team_id": "24", "position": "MF", "trend": 2}, {"first_name": "Luca", "last_name": "Kilian", "price": 2319623.0, "expiration": "2023-01-29T04:33:11.669564+01:00", "team_id": "28", "position": "ABW", "trend": 2}, {"first_name": "Tom", "last_name": "Krau\u00df", "price": 3631311.0, "expiration": "2023-01-28T17:50:31.669576+01:00", "team_id": "8", "position": "MF", "trend": 2}, {"first_name": "Jakob", "last_name": "Busk", "price": 500000.0, "expiration": "2023-01-29T04:21:58.257021+01:00", "team_id": "40", "position": "TW", "trend": 0}, {"first_name": "Hannes", "last_name": "Wolf", "price": 1663668.0, "expiration": "2023-01-28T11:10:08.257059+01:00", "team_id": "15", "position": "MF", "trend": 1}, {"first_name": "Iago Amaral", "last_name": "Borduchi", "price": 2816668.0, "expiration": "2023-01-28T12:45:46.257072+01:00", "team_id": "13", "position": "ABW", "trend": 2}, {"first_name": "Ruben", "last_name": "Vargas", "price": 3280598.0, "expiration": "2023-01-29T07:12:23.257081+01:00", "team_id": "13", "position": "MF", "trend": 2}, {"first_name": "Exequiel", "last_name": "Palacios", "price": 8482291.0, "expiration": "2023-01-28T21:13:14.257092+01:00", "team_id": "7", "position": "MF", "trend": 1}, {"first_name": "Tim", "last_name": "Lemperle", "price": 1295521.0, "expiration": "2023-01-29T03:08:29.257102+01:00", "team_id": "28", "position": "ANG", "trend": 1}, {"first_name": "Marcel Laurenz", "last_name": "Lotka", "price": 500000.0, "expiration": "2023-01-29T08:16:58.257112+01:00", "team_id": "3", "position": "TW", "trend": 0}, {"first_name": "Paul", "last_name": "Grave", "price": 500000.0, "expiration": "2023-01-29T10:52:58.834327+01:00", "team_id": "24", "position": "TW", "trend": 0}, {"first_name": "Lasse Finn", "last_name": "Rie\u00df", "price": 500000.0, "expiration": "2023-01-29T18:03:44.422364+01:00", "team_id": "18", "position": "TW", "trend": 0}, {"first_name": "Aur\u00e9lio Gabriel", "last_name": "Ulineia Buta", "price": 3307889.0, "expiration": "2023-01-29T23:46:40.899161+01:00", "team_id": "4", "position": "ABW", "trend": 1}, {"first_name": "Elias-Geoffrey", "last_name": "Bakatukanda", "price": 675115.0, "expiration": "2023-01-28T15:31:29.474417+01:00", "team_id": "28", "position": "ABW", "trend": 1}, {"first_name": "Moritz", "last_name": "Jenz", "price": 3815138.0, "expiration": "2023-01-29T04:32:21.062444+01:00", "team_id": "8", "position": "ABW", "trend": 1}]