[{"first_name": "Jens", "last_name": "Grahl", "price": 500000.0, "expiration": "2022-11-02T15:55:02.060075+01:00", "team_id": "4"}, {"first_name": "Tony", "last_name": "Jantschke", "price": 608045.0, "expiration": "2022-11-04T09:02:13.060126+01:00", "team_id": "15"}, {"first_name": "Rune", "last_name": "Jarstein", "price": 500000.0, "expiration": "2022-11-03T11:30:49.060147+01:00", "team_id": "20"}, {"first_name": "Rapha\u00ebl", "last_name": "Guerreiro", "price": 25487505.0, "expiration": "2022-11-03T01:52:45.060167+01:00", "team_id": "3"}, {"first_name": "Alexander", "last_name": "Meyer", "price": 3170242.0, "expiration": "2022-11-02T16:10:06.060183+01:00", "team_id": "3"}, {"first_name": "Lucas", "last_name": "H\u00f6ler", "price": 6574217.0, "expiration": "2022-11-03T04:56:18.060194+01:00", "team_id": "5"}, {"first_name": "Leandro", "last_name": "Barreiro Martins", "price": 4612388.0, "expiration": "2022-11-03T00:11:20.060207+01:00", "team_id": "18"}, {"first_name": "Antonis", "last_name": "Aidonis", "price": 500000.0, "expiration": "2022-11-03T06:13:54.060219+01:00", "team_id": "9"}, {"first_name": "Eric", "last_name": "Martel", "price": 4100078.0, "expiration": "2022-11-03T13:16:19.060234+01:00", "team_id": "28"}, {"first_name": "Christian", "last_name": "Gro\u00df", "price": 4314799.0, "expiration": "2022-11-03T03:40:07.060245+01:00", "team_id": "10"}, {"first_name": "Jan", "last_name": "Thielmann", "price": 3445977.0, "expiration": "2022-11-03T23:25:42.060256+01:00", "team_id": "28"}, {"first_name": "Jessic", "last_name": "Ngankam", "price": 500000.0, "expiration": "2022-11-04T00:37:35.060266+01:00", "team_id": "20"}, {"first_name": "Tanguy", "last_name": "Coulibaly", "price": 826374.0, "expiration": "2022-11-03T01:57:34.060278+01:00", "team_id": "9"}, {"first_name": "Noah", "last_name": "Atubolu", "price": 500000.0, "expiration": "2022-11-02T15:07:11.060291+01:00", "team_id": "5"}, {"first_name": "Donyell", "last_name": "Malen", "price": 13403902.0, "expiration": "2022-11-03T06:54:51.060302+01:00", "team_id": "3"}, {"first_name": "Micky", "last_name": "van de Ven", "price": 10098464.0, "expiration": "2022-11-02T15:49:33.060312+01:00", "team_id": "11"}, {"first_name": "Lion", "last_name": "Semi\u0107", "price": 500000.0, "expiration": "2022-11-03T13:23:35.060322+01:00", "team_id": "3"}, {"first_name": "Lee", "last_name": "Buchanan", "price": 2310057.0, "expiration": "2022-11-04T09:33:01.060334+01:00", "team_id": "10"}, {"first_name": "Muhammed", "last_name": "Damar", "price": 500000.0, "expiration": "2022-11-04T10:31:14.060344+01:00", "team_id": "14"}]