[{"first_name": "Niko", "last_name": "Gie\u00dfelmann", "price": 11011353.0, "expiration": "2022-10-27T09:56:49.550284+02:00", "team_id": "40"}, {"first_name": "Kevin", "last_name": "Vogt", "price": 9947909.0, "expiration": "2022-10-26T19:43:23.550320+02:00", "team_id": "14"}, {"first_name": "Karim", "last_name": "Bellarabi", "price": 2363415.0, "expiration": "2022-10-26T16:13:11.550329+02:00", "team_id": "7"}, {"first_name": "Dominick", "last_name": "Drexler", "price": 4521424.0, "expiration": "2022-10-27T00:33:10.550337+02:00", "team_id": "8"}, {"first_name": "Peter", "last_name": "Pekar\u00edk", "price": 500000.0, "expiration": "2022-10-26T23:04:21.550345+02:00", "team_id": "20"}, {"first_name": "Vladimir", "last_name": "Darida", "price": 500000.0, "expiration": "2022-10-26T16:12:27.550352+02:00", "team_id": "20"}, {"first_name": "Janik", "last_name": "Haberer", "price": 12149183.0, "expiration": "2022-10-28T00:30:44.550359+02:00", "team_id": "40"}, {"first_name": "Thorgan", "last_name": "Hazard", "price": 6181036.0, "expiration": "2022-10-27T16:06:54.550366+02:00", "team_id": "3"}, {"first_name": "Josha", "last_name": "Vagnoman", "price": 1934518.0, "expiration": "2022-10-26T21:55:29.550374+02:00", "team_id": "9"}, {"first_name": "Keven", "last_name": "Schlotterbeck", "price": 522739.0, "expiration": "2022-10-26T17:42:45.550381+02:00", "team_id": "5"}, {"first_name": "Patrick", "last_name": "Osterhage", "price": 2082777.0, "expiration": "2022-10-26T17:02:50.550390+02:00", "team_id": "24"}, {"first_name": "Luca", "last_name": "Netz", "price": 1584030.0, "expiration": "2022-10-27T17:34:26.550397+02:00", "team_id": "15"}, {"first_name": "Felix", "last_name": "Agu", "price": 500000.0, "expiration": "2022-10-26T19:18:48.550404+02:00", "team_id": "10"}, {"first_name": "Tim", "last_name": "Maciejewski", "price": 500000.0, "expiration": "2022-10-26T16:37:15.550410+02:00", "team_id": "40"}, {"first_name": "Jonas", "last_name": "Urbig", "price": 500000.0, "expiration": "2022-10-28T03:54:44.550418+02:00", "team_id": "28"}, {"first_name": "Amine", "last_name": "Adli", "price": 4524589.0, "expiration": "2022-10-27T11:59:54.550425+02:00", "team_id": "7"}, {"first_name": "Jens", "last_name": "Stage", "price": 2312024.0, "expiration": "2022-10-26T23:21:41.550432+02:00", "team_id": "10"}, {"first_name": "Justin", "last_name": "Heekeren", "price": 500000.0, "expiration": "2022-10-27T04:44:30.550439+02:00", "team_id": "8"}, {"first_name": "Maya", "last_name": "Yoshida", "price": 6969880.0, "expiration": "2022-10-27T16:32:53.550446+02:00", "team_id": "8"}, {"first_name": "Thomas", "last_name": "Kastanaras", "price": 500000.0, "expiration": "2022-10-27T13:18:10.550452+02:00", "team_id": "9"}]