[{"first_name": "Benjamin", "last_name": "Pavard", "team_id": "2", "market_value": 27562755.0, "buy_price": 36000000.0, "user": "Alex", "player_id": "2054", "date": "2022-08-22T11:29:39+00:00", "position": "ABW", "trend": 1}, {"first_name": "Jamal", "last_name": "Musiala", "team_id": "2", "market_value": 47483710.0, "buy_price": 51000000.0, "user": "Alex", "player_id": "2804", "date": "2022-08-23T01:34:55+00:00", "position": "MF", "trend": 1}, {"first_name": "Ko", "last_name": "Itakura", "team_id": "15", "market_value": 17930310.0, "buy_price": 9900000.0, "user": "Alex", "player_id": "3129", "date": "2022-10-14T00:07:06+00:00", "position": "ABW", "trend": 2}, {"first_name": "Bote", "last_name": "Baku", "team_id": "11", "market_value": 22150390.0, "buy_price": 13900000.0, "user": "Alex", "player_id": "2141", "date": "2022-10-19T12:57:11+00:00", "position": "MF", "trend": 2}, {"first_name": "Wataru", "last_name": "Endo", "team_id": "9", "market_value": 15945659.0, "buy_price": 13660000.0, "user": "Alex", "player_id": "2837", "date": "2022-10-23T07:35:37+00:00", "position": "MF", "trend": 1}, {"first_name": "Xaver", "last_name": "Schlager", "team_id": "43", "market_value": 15211973.0, "buy_price": 10700000.0, "user": "Alex", "player_id": "2649", "date": "2022-11-01T12:52:46+00:00", "position": "MF", "trend": 2}, {"first_name": "Mark", "last_name": "Flekken", "team_id": "5", "market_value": 22579087.0, "buy_price": 31500000.0, "user": "Alex", "player_id": "72", "date": "2022-11-10T19:35:59+00:00", "position": "TW", "trend": 2}, {"first_name": "M\u00ebrgim", "last_name": "Berisha", "team_id": "13", "market_value": 13308658.0, "buy_price": 7730000.0, "user": "Alex", "player_id": "4421", "date": "2023-01-10T00:54:12+00:00", "position": "ANG", "trend": 1}, {"first_name": "Piero", "last_name": "Hincapi\u00e9", "team_id": "7", "market_value": 12511684.0, "buy_price": 11250000.0, "user": "Alex", "player_id": "3128", "date": "2023-01-17T02:52:58+00:00", "position": "ABW", "trend": 1}, {"first_name": "Lukas", "last_name": "K\u00fcbler", "team_id": "5", "market_value": 15832939.0, "buy_price": 14150000.0, "user": "Alex", "player_id": "1257", "date": "2023-01-25T06:49:15+00:00", "position": "ABW", "trend": 1}, {"first_name": "Jeffrey", "last_name": "Gouweleeuw", "team_id": "13", "market_value": 10627042.0, "buy_price": 13350000.0, "user": "Alex", "player_id": "1811", "date": "2023-02-08T19:14:57+00:00", "position": "ABW", "trend": 1}, {"first_name": "Patrik", "last_name": "Schick", "team_id": "7", "market_value": 18918545.0, "buy_price": 47266669.0, "user": "BeNice", "player_id": "2746", "date": "2022-08-04T22:09:10+00:00", "position": "ANG", "trend": 1}, {"first_name": "Moussa", "last_name": "Diaby", "team_id": "7", "market_value": 35053114.0, "buy_price": 46255622.0, "user": "BeNice", "player_id": "2661", "date": "2022-08-12T14:47:57+00:00", "position": "ANG", "trend": 2}, {"first_name": "Dominik", "last_name": "Szoboszlai", "team_id": "43", "market_value": 30866676.0, "buy_price": 17779126.0, "user": "BeNice", "player_id": "2940", "date": "2022-09-06T18:29:29+00:00", "position": "MF", "trend": 1}, {"first_name": "Thomas", "last_name": "M\u00fcller", "team_id": "2", "market_value": 37274695.0, "buy_price": 47888999.0, "user": "BeNice", "player_id": "450", "date": "2022-09-22T09:55:01+00:00", "position": "MF", "trend": 1}, {"first_name": "Kingsley", "last_name": "Coman", "team_id": "2", "market_value": 29165881.0, "buy_price": 33556656.0, "user": "BeNice", "player_id": "1774", "date": "2022-10-01T00:36:08+00:00", "position": "MF", "trend": 1}, {"first_name": "Marco", "last_name": "Reus", "team_id": "3", "market_value": 27939016.0, "buy_price": 37788999.0, "user": "BeNice", "player_id": "399", "date": "2022-10-14T17:39:24+00:00", "position": "MF", "trend": 1}, {"first_name": "Rapha\u00ebl", "last_name": "Guerreiro", "team_id": "3", "market_value": 26837522.0, "buy_price": 26889683.0, "user": "BeNice", "player_id": "1862", "date": "2022-11-03T00:53:10+00:00", "position": "ABW", "trend": 1}, {"first_name": "Jo\u0161ko", "last_name": "Gvardiol", "team_id": "43", "market_value": 24186530.0, "buy_price": 15989808.0, "user": "BeNice", "player_id": "3003", "date": "2022-11-12T00:29:53+00:00", "position": "ABW", "trend": 1}, {"first_name": "Obite", "last_name": "Ndicka", "team_id": "4", "market_value": 20967127.0, "buy_price": 18666666.0, "user": "BeNice", "player_id": "2282", "date": "2022-11-30T13:23:08+00:00", "position": "ABW", "trend": 1}, {"first_name": "Djibril", "last_name": "Sow", "team_id": "4", "market_value": 15376799.0, "buy_price": 13750000.0, "user": "BeNice", "player_id": "1738", "date": "2023-01-15T15:35:34+00:00", "position": "MF", "trend": 1}, {"first_name": "Jamie Jermaine", "last_name": "Bynoe-Gittens", "team_id": "3", "market_value": 12162292.0, "buy_price": 11025800.0, "user": "BeNice", "player_id": "3219", "date": "2023-01-26T13:54:50+00:00", "position": "MF", "trend": 1}, {"first_name": "Ludovic", "last_name": "Ajorque", "team_id": "18", "market_value": 10211921.0, "buy_price": 12222229.0, "user": "BeNice", "player_id": "4600", "date": "2023-01-27T11:50:04+00:00", "position": "ANG", "trend": 1}, {"first_name": "Oliver", "last_name": "Baumann", "team_id": "14", "market_value": 8807032.0, "buy_price": 10733813.0, "user": "BeNice", "player_id": "524", "date": "2023-01-29T06:53:34+00:00", "position": "TW", "trend": 2}, {"first_name": "Philipp", "last_name": "Max", "team_id": "4", "market_value": 14529187.0, "buy_price": 15555559.0, "user": "BeNice", "player_id": "1217", "date": "2023-02-02T11:51:28+00:00", "position": "ABW", "trend": 1}, {"first_name": "Arne", "last_name": "Engels", "team_id": "13", "market_value": 12050334.0, "buy_price": 15956595.0, "user": "BeNice", "player_id": "4555", "date": "2023-02-10T13:51:21+00:00", "position": "MF", "trend": 1}, {"first_name": "Noussair", "last_name": "Mazraoui", "team_id": "2", "market_value": 9669111.0, "buy_price": 27066666.0, "user": "BeNice", "player_id": "3477", "date": "2023-02-17T20:51:58+00:00", "position": "ABW", "trend": 1}, {"first_name": "Lars", "last_name": "Stindl", "team_id": "15", "market_value": 15722230.0, "buy_price": 21559555.0, "user": "BeNice", "player_id": "393", "date": "2023-02-20T17:55:22+00:00", "position": "MF", "trend": 1}, {"first_name": "Marvin", "last_name": "Schw\u00e4be", "team_id": "28", "market_value": 8354224.0, "buy_price": 8354229.0, "user": "BeNice", "player_id": "1580", "date": "2023-02-21T00:39:50+00:00", "position": "TW", "trend": 1}, {"first_name": "Marcus", "last_name": "Thuram", "team_id": "15", "market_value": 29419010.0, "buy_price": 17678678.0, "user": "Juli\u00e1n", "player_id": "2704", "date": "2022-07-24T15:01:50+00:00", "position": "ANG", "trend": 2}, {"first_name": "Alassane", "last_name": "Plea", "team_id": "15", "market_value": 19580369.0, "buy_price": 31543210.0, "user": "Juli\u00e1n", "player_id": "2288", "date": "2022-07-24T17:30:32+00:00", "position": "ANG", "trend": 2}, {"first_name": "Nico", "last_name": "Elvedi", "team_id": "15", "market_value": 19359240.0, "buy_price": 16666666.0, "user": "Juli\u00e1n", "player_id": "1686", "date": "2022-08-09T15:48:27+00:00", "position": "ABW", "trend": 1}, {"first_name": "Mark", "last_name": "Uth", "team_id": "28", "market_value": 500000.0, "buy_price": 9467899.0, "user": "Juli\u00e1n", "player_id": "1725", "date": "2022-09-28T17:05:45+00:00", "position": "MF", "trend": 0}, {"first_name": "Jonas", "last_name": "Wind", "team_id": "11", "market_value": 14129713.0, "buy_price": 9876543.0, "user": "Juli\u00e1n", "player_id": "3196", "date": "2022-10-24T07:22:31+00:00", "position": "ANG", "trend": 2}, {"first_name": "Robert", "last_name": "Andrich", "team_id": "7", "market_value": 13842925.0, "buy_price": 12888888.0, "user": "Juli\u00e1n", "player_id": "663", "date": "2022-11-12T01:37:10+00:00", "position": "MF", "trend": 1}, {"first_name": "Jonas", "last_name": "Hector", "team_id": "28", "market_value": 14687752.0, "buy_price": 18666677.0, "user": "Juli\u00e1n", "player_id": "1256", "date": "2022-11-21T17:27:00+00:00", "position": "MF", "trend": 1}, {"first_name": "Borna", "last_name": "Sosa", "team_id": "9", "market_value": 15320514.0, "buy_price": 17333666.0, "user": "Juli\u00e1n", "player_id": "2247", "date": "2022-11-29T16:12:39+00:00", "position": "ABW", "trend": 1}, {"first_name": "Philipp", "last_name": "Lienhart", "team_id": "5", "market_value": 22672885.0, "buy_price": 22345679.0, "user": "Juli\u00e1n", "player_id": "2084", "date": "2023-01-01T02:48:37+00:00", "position": "ABW", "trend": 1}, {"first_name": "S\u00e9bastien", "last_name": "Haller", "team_id": "3", "market_value": 20385708.0, "buy_price": 28666677.0, "user": "Juli\u00e1n", "player_id": "2037", "date": "2023-01-11T21:46:28+00:00", "position": "ANG", "trend": 1}, {"first_name": "Julian", "last_name": "Chabot", "team_id": "28", "market_value": 13846080.0, "buy_price": 16543210.0, "user": "Juli\u00e1n", "player_id": "3190", "date": "2023-02-03T00:31:58+00:00", "position": "ABW", "trend": 1}, {"first_name": "Jiri", "last_name": "Pavlenka", "team_id": "10", "market_value": 11900211.0, "buy_price": 14321051.0, "user": "Juli\u00e1n", "player_id": "2053", "date": "2023-02-06T11:06:35+00:00", "position": "TW", "trend": 1}, {"first_name": "Ralf", "last_name": "F\u00e4hrmann", "team_id": "8", "market_value": 7472693.0, "buy_price": 6789123.0, "user": "Juli\u00e1n", "player_id": "262", "date": "2023-02-12T22:25:38+00:00", "position": "TW", "trend": 1}, {"first_name": "Christoph", "last_name": "Kramer", "team_id": "15", "market_value": 9294943.0, "buy_price": 9456789.0, "user": "Juli\u00e1n", "player_id": "8", "date": "2023-02-17T02:14:10+00:00", "position": "MF", "trend": 2}, {"first_name": "Luca", "last_name": "Kilian", "team_id": "28", "market_value": 1506364.0, "buy_price": 777777.0, "user": "Juli\u00e1n", "player_id": "2349", "date": "2023-02-18T12:53:22+00:00", "position": "ABW", "trend": 1}, {"first_name": "Thomas", "last_name": "Meunier", "team_id": "3", "market_value": 3673022.0, "buy_price": 5432109.0, "user": "Juli\u00e1n", "player_id": "2835", "date": "2023-02-19T13:57:58+00:00", "position": "ABW", "trend": 2}, {"first_name": "Roland", "last_name": "Sallai", "team_id": "5", "market_value": 4311873.0, "buy_price": 4876543.0, "user": "Juli\u00e1n", "player_id": "2343", "date": "2023-02-20T21:35:51+00:00", "position": "MF", "trend": 1}, {"first_name": "Sadio", "last_name": "Man\u00e9", "team_id": "2", "market_value": 34900666.0, "buy_price": 60212233.0, "user": "Jimmy", "player_id": "3478", "date": "2022-07-22T01:23:04+00:00", "position": "ANG", "trend": 1}, {"first_name": "Joshua", "last_name": "Kimmich", "team_id": "2", "market_value": 50363015.0, "buy_price": 61187187.0, "user": "Jimmy", "player_id": "1685", "date": "2022-08-04T04:57:21+00:00", "position": "MF", "trend": 1}, {"first_name": "Mario", "last_name": "G\u00f6tze", "team_id": "4", "market_value": 23790221.0, "buy_price": 19352121.0, "user": "Jimmy", "player_id": "513", "date": "2022-09-06T21:02:53+00:00", "position": "MF", "trend": 1}, {"first_name": "Anton", "last_name": "Stach", "team_id": "18", "market_value": 10061471.0, "buy_price": 11123826.0, "user": "Jimmy", "player_id": "2987", "date": "2022-09-28T20:13:33+00:00", "position": "MF", "trend": 1}, {"first_name": "Koen", "last_name": "Casteels", "team_id": "11", "market_value": 19744362.0, "buy_price": 13110808.0, "user": "Jimmy", "player_id": "497", "date": "2022-10-01T20:47:14+00:00", "position": "TW", "trend": 2}, {"first_name": "Andrej", "last_name": "Kramaric", "team_id": "14", "market_value": 17549803.0, "buy_price": 29187187.0, "user": "Jimmy", "player_id": "1815", "date": "2022-10-05T07:07:43+00:00", "position": "ANG", "trend": 2}, {"first_name": "Eric Maxim", "last_name": "Choupo-Moting", "team_id": "2", "market_value": 25594998.0, "buy_price": 2812586.0, "user": "Jimmy", "player_id": "336", "date": "2022-10-08T05:17:29+00:00", "position": "ANG", "trend": 1}, {"first_name": "Andr\u00e9 Miguel", "last_name": "Valente Silva", "team_id": "43", "market_value": 21849052.0, "buy_price": 20000009.0, "user": "Jimmy", "player_id": "2747", "date": "2022-10-18T02:07:09+00:00", "position": "ANG", "trend": 1}, {"first_name": "Leon", "last_name": "Goretzka", "team_id": "2", "market_value": 31036574.0, "buy_price": 35645680.0, "user": "Jimmy", "player_id": "660", "date": "2022-10-22T07:53:00+00:00", "position": "MF", "trend": 1}, {"first_name": "Niklas", "last_name": "S\u00fcle", "team_id": "3", "market_value": 22915719.0, "buy_price": 17928009.0, "user": "Jimmy", "player_id": "163", "date": "2022-12-07T18:54:27+00:00", "position": "ABW", "trend": 1}, {"first_name": "Robin", "last_name": "Knoche", "team_id": "40", "market_value": 19196994.0, "buy_price": 15920109.0, "user": "Jimmy", "player_id": "623", "date": "2022-12-19T04:39:19+00:00", "position": "ABW", "trend": 1}, {"first_name": "Milos", "last_name": "Veljkovic", "team_id": "10", "market_value": 7455228.0, "buy_price": 12695699.0, "user": "Jimmy", "player_id": "1823", "date": "2022-12-23T09:41:40+00:00", "position": "ABW", "trend": 2}, {"first_name": "Waldemar", "last_name": "Anton", "team_id": "9", "market_value": 7722142.0, "buy_price": 7923636.0, "user": "Jimmy", "player_id": "1704", "date": "2023-01-09T03:13:40+00:00", "position": "ABW", "trend": 2}, {"first_name": "Janik", "last_name": "Haberer", "team_id": "40", "market_value": 12329322.0, "buy_price": 7101250.0, "user": "Jimmy", "player_id": "1553", "date": "2023-01-20T12:25:20+00:00", "position": "MF", "trend": 1}, {"first_name": "Edimilson", "last_name": "Fernandes", "team_id": "18", "market_value": 8099727.0, "buy_price": 8001008.0, "user": "Jimmy", "player_id": "2643", "date": "2023-02-04T07:48:02+00:00", "position": "MF", "trend": 1}, {"first_name": "Marco", "last_name": "Friedl", "team_id": "10", "market_value": 9287841.0, "buy_price": 9212509.0, "user": "Jimmy", "player_id": "1996", "date": "2023-02-10T20:57:35+00:00", "position": "ABW", "trend": 1}, {"first_name": "Marius", "last_name": "Wolf", "team_id": "3", "market_value": 10351920.0, "buy_price": 9581010.0, "user": "Jimmy", "player_id": "1809", "date": "2023-02-13T11:50:43+00:00", "position": "MF", "trend": 1}, {"first_name": "Dodi", "last_name": "Luk\u00e9bakio", "team_id": "20", "market_value": 14661903.0, "buy_price": 0, "user": "Stephan", "player_id": "2308", "date": "2022-07-01T00:00:00+00:53", "position": "ANG", "trend": 1}, {"first_name": "Christopher", "last_name": "Nkunku", "team_id": "43", "market_value": 41647412.0, "buy_price": 57329419.0, "user": "Stephan", "player_id": "2687", "date": "2022-07-26T23:38:14+00:00", "position": "ANG", "trend": 1}, {"first_name": "Alphonso", "last_name": "Davies", "team_id": "2", "market_value": 34533459.0, "buy_price": 42000000.0, "user": "Stephan", "player_id": "2366", "date": "2022-08-05T00:45:10+00:00", "position": "ABW", "trend": 1}, {"first_name": "Maximilian", "last_name": "Arnold", "team_id": "11", "market_value": 27786708.0, "buy_price": 23529419.0, "user": "Stephan", "player_id": "44", "date": "2022-09-23T19:45:11+00:00", "position": "MF", "trend": 2}, {"first_name": "Dani", "last_name": "Olmo", "team_id": "43", "market_value": 17877728.0, "buy_price": 19235294.0, "user": "Stephan", "player_id": "2776", "date": "2022-10-09T08:07:40+00:00", "position": "MF", "trend": 1}, {"first_name": "Gregor", "last_name": "Kobel", "team_id": "3", "market_value": 22464736.0, "buy_price": 19429419.0, "user": "Stephan", "player_id": "1873", "date": "2022-10-22T08:22:47+00:00", "position": "TW", "trend": 1}, {"first_name": "Nico", "last_name": "Schlotterbeck", "team_id": "3", "market_value": 37077058.0, "buy_price": 35550000.0, "user": "Stephan", "player_id": "2383", "date": "2022-10-25T20:13:39+00:00", "position": "ABW", "trend": 1}, {"first_name": "Konrad", "last_name": "Laimer", "team_id": "43", "market_value": 11331586.0, "buy_price": 9573294.0, "user": "Stephan", "player_id": "2038", "date": "2022-11-12T21:28:39+00:00", "position": "MF", "trend": 2}, {"first_name": "Ozan", "last_name": "Kabak", "team_id": "14", "market_value": 16381401.0, "buy_price": 19352904.0, "user": "Stephan", "player_id": "2373", "date": "2022-11-20T00:22:51+00:00", "position": "ABW", "trend": 1}, {"first_name": "Jo\u00e3o Pedro", "last_name": "Cavaco Cancelo", "team_id": "2", "market_value": 36647628.0, "buy_price": 75329419.0, "user": "Stephan", "player_id": "4628", "date": "2023-02-02T09:21:16+00:00", "position": "ABW", "trend": 1}, {"first_name": "Lucas", "last_name": "H\u00f6ler", "team_id": "5", "market_value": 9451651.0, "buy_price": 7529419.0, "user": "Stephan", "player_id": "2176", "date": "2023-02-04T07:32:59+00:00", "position": "ANG", "trend": 1}, {"first_name": "Kevin", "last_name": "Behrens", "team_id": "40", "market_value": 10105044.0, "buy_price": 9375294.0, "user": "Stephan", "player_id": "2496", "date": "2023-02-05T05:57:46+00:00", "position": "ANG", "trend": 1}, {"first_name": "Felix", "last_name": "Uduokhai", "team_id": "13", "market_value": 7069947.0, "buy_price": 6735294.0, "user": "Stephan", "player_id": "2065", "date": "2023-02-13T14:20:32+00:00", "position": "ABW", "trend": 1}, {"first_name": "Timo", "last_name": "H\u00fcbers", "team_id": "28", "market_value": 9956719.0, "buy_price": 9735294.0, "user": "Stephan", "player_id": "2069", "date": "2023-02-18T17:27:39+00:00", "position": "ABW", "trend": 1}, {"first_name": "Nadiem", "last_name": "Amiri", "team_id": "7", "market_value": 5659253.0, "buy_price": 6429419.0, "user": "Stephan", "player_id": "1639", "date": "2023-02-20T08:28:41+00:00", "position": "MF", "trend": 2}, {"first_name": "Ansgar", "last_name": "Knauff", "team_id": "4", "market_value": 7118878.0, "buy_price": 7735294.0, "user": "Stephan", "player_id": "2863", "date": "2023-02-20T23:49:13+00:00", "position": "MF", "trend": 2}, {"first_name": "Ritsu", "last_name": "D\u014dan", "team_id": "5", "market_value": 21304130.0, "buy_price": 0, "user": "Roman", "player_id": "2887", "date": "2022-07-01T00:00:00+00:53", "position": "MF", "trend": 1}, {"first_name": "Jeremie", "last_name": "Frimpong", "team_id": "7", "market_value": 24146814.0, "buy_price": 16400000.0, "user": "Roman", "player_id": "2948", "date": "2022-08-24T17:18:49+00:00", "position": "ABW", "trend": 1}, {"first_name": "Serge", "last_name": "Gnabry", "team_id": "2", "market_value": 34751700.0, "buy_price": 33650000.0, "user": "Roman", "player_id": "1961", "date": "2022-10-10T21:43:33+00:00", "position": "MF", "trend": 1}, {"first_name": "Konstantinos", "last_name": "Mavropanos", "team_id": "9", "market_value": 25132239.0, "buy_price": 26123000.0, "user": "Roman", "player_id": "2838", "date": "2022-10-20T19:22:34+00:00", "position": "ABW", "trend": 1}, {"first_name": "Jesper", "last_name": "Lindstr\u00f8m", "team_id": "4", "market_value": 21371329.0, "buy_price": 21345000.0, "user": "Roman", "player_id": "3044", "date": "2022-11-04T02:25:44+00:00", "position": "MF", "trend": 1}, {"first_name": "Jonas", "last_name": "Hofmann", "team_id": "15", "market_value": 30420261.0, "buy_price": 44567000.0, "user": "Roman", "player_id": "78", "date": "2022-11-09T15:35:16+00:00", "position": "MF", "trend": 1}, {"first_name": "Mitchell", "last_name": "Weiser", "team_id": "10", "market_value": 16605925.0, "buy_price": 18789000.0, "user": "Roman", "player_id": "43", "date": "2022-11-15T09:16:59+00:00", "position": "ABW", "trend": 1}, {"first_name": "Rafal", "last_name": "Gikiewicz", "team_id": "13", "market_value": 18230589.0, "buy_price": 17350000.0, "user": "Roman", "player_id": "1936", "date": "2022-11-24T10:16:24+00:00", "position": "TW", "trend": 1}, {"first_name": "Christian", "last_name": "G\u00fcnter", "team_id": "5", "market_value": 21380440.0, "buy_price": 22160000.0, "user": "Roman", "player_id": "89", "date": "2022-12-09T00:56:57+00:00", "position": "ABW", "trend": 2}, {"first_name": "Emil", "last_name": "Forsberg", "team_id": "43", "market_value": 10847846.0, "buy_price": 10600000.0, "user": "Roman", "player_id": "1900", "date": "2023-01-27T19:05:29+00:00", "position": "MF", "trend": 1}, {"first_name": "Salih", "last_name": "\u00d6zcan", "team_id": "3", "market_value": 10992484.0, "buy_price": 9210000.0, "user": "Roman", "player_id": "1918", "date": "2023-01-23T12:01:51+00:00", "position": "MF", "trend": 1}, {"first_name": "John Anthony", "last_name": "Brooks", "team_id": "14", "market_value": 8459418.0, "buy_price": 6780000.0, "user": "Roman", "player_id": "651", "date": "2023-01-28T21:43:15+00:00", "position": "ABW", "trend": 1}, {"first_name": "Danilho", "last_name": "Doekhi", "team_id": "40", "market_value": 17731139.0, "buy_price": 21090419.0, "user": "Roman", "player_id": "3473", "date": "2023-02-02T09:31:30+00:00", "position": "ABW", "trend": 1}, {"first_name": "Lukas", "last_name": "Nmecha", "team_id": "11", "market_value": 7690798.0, "buy_price": 6850000.0, "user": "Roman", "player_id": "2724", "date": "2023-02-10T16:02:07+00:00", "position": "ANG", "trend": 1}, {"first_name": "Donyell", "last_name": "Malen", "team_id": "3", "market_value": 9278999.0, "buy_price": 11234000.0, "user": "Roman", "player_id": "3087", "date": "2023-02-20T21:04:11+00:00", "position": "ANG", "trend": 1}, {"first_name": "Jude", "last_name": "Bellingham", "team_id": "3", "market_value": 50449521.0, "buy_price": 46282645.0, "user": "u77e", "player_id": "2845", "date": "2022-08-01T02:46:58+00:00", "position": "MF", "trend": 1}, {"first_name": "Ramy", "last_name": "Bensebaini", "team_id": "15", "market_value": 26297631.0, "buy_price": 22109786.0, "user": "u77e", "player_id": "2736", "date": "2022-08-12T09:22:43+00:00", "position": "ABW", "trend": 1}, {"first_name": "Florian", "last_name": "Wirtz", "team_id": "7", "market_value": 29012220.0, "buy_price": 20175600.0, "user": "u77e", "player_id": "2795", "date": "2022-09-13T03:08:13+00:00", "position": "MF", "trend": 1}, {"first_name": "Dan-Axel", "last_name": "Zagadou", "team_id": "9", "market_value": 1273489.0, "buy_price": 9828780.0, "user": "u77e", "player_id": "2068", "date": "2022-09-25T00:27:43+00:00", "position": "ABW", "trend": 2}, {"first_name": "Marc-Oliver", "last_name": "Kempf", "team_id": "20", "market_value": 7429917.0, "buy_price": 9244653.0, "user": "u77e", "player_id": "99", "date": "2022-10-09T07:56:12+00:00", "position": "ABW", "trend": 1}, {"first_name": "Karim", "last_name": "Onisiwo", "team_id": "18", "market_value": 14240612.0, "buy_price": 18909000.0, "user": "u77e", "player_id": "1804", "date": "2022-10-25T07:11:40+00:00", "position": "ANG", "trend": 1}, {"first_name": "Suat", "last_name": "Serdar", "team_id": "20", "market_value": 4587196.0, "buy_price": 15200555.0, "user": "u77e", "player_id": "1790", "date": "2022-10-26T03:06:01+00:00", "position": "MF", "trend": 2}, {"first_name": "Julian", "last_name": "Brandt", "team_id": "3", "market_value": 28983108.0, "buy_price": 36055555.0, "user": "u77e", "player_id": "1192", "date": "2022-10-28T23:23:57+00:00", "position": "MF", "trend": 1}, {"first_name": "Jonathan", "last_name": "Burkardt", "team_id": "18", "market_value": 782337.0, "buy_price": 7956320.0, "user": "u77e", "player_id": "2255", "date": "2022-11-30T16:51:51+00:00", "position": "ANG", "trend": 2}, {"first_name": "Giovanni", "last_name": "Reyna", "team_id": "3", "market_value": 14505039.0, "buy_price": 13200000.0, "user": "u77e", "player_id": "2692", "date": "2023-02-02T15:04:55+00:00", "position": "MF", "trend": 1}, {"first_name": "Jonas", "last_name": "Omlin", "team_id": "15", "market_value": 14581513.0, "buy_price": 15278908.0, "user": "u77e", "player_id": "4590", "date": "2023-01-22T23:10:28+00:00", "position": "TW", "trend": 2}, {"first_name": "Nelson", "last_name": "Weiper", "team_id": "18", "market_value": 500000.0, "buy_price": 510000.0, "user": "u77e", "player_id": "4460", "date": "2023-01-23T23:46:39+00:00", "position": "ANG", "trend": 0}, {"first_name": "Sebastiaan", "last_name": "Bornauw", "team_id": "11", "market_value": 9878929.0, "buy_price": 15298064.0, "user": "u77e", "player_id": "2725", "date": "2023-01-27T10:19:40+00:00", "position": "ABW", "trend": 2}, {"first_name": "Florian", "last_name": "Niederlechner", "team_id": "20", "market_value": 5821549.0, "buy_price": 5888975.0, "user": "u77e", "player_id": "1680", "date": "2023-02-06T21:41:17+00:00", "position": "ANG", "trend": 2}, {"first_name": "Marco", "last_name": "Richter", "team_id": "20", "market_value": 4823963.0, "buy_price": 5300000.0, "user": "u77e", "player_id": "2092", "date": "2023-02-17T14:53:27+00:00", "position": "MF", "trend": 1}, {"first_name": "Umut", "last_name": "Tohumcu", "team_id": "14", "market_value": 2607079.0, "buy_price": 2457808.0, "user": "u77e", "player_id": "3230", "date": "2023-02-18T16:43:21+00:00", "position": "MF", "trend": 1}, {"first_name": "Anthony", "last_name": "Jung", "team_id": "10", "market_value": 7492841.0, "buy_price": 7856508.0, "user": "u77e", "player_id": "1858", "date": "2023-02-19T21:14:09+00:00", "position": "ABW", "trend": 1}, {"first_name": "Willi", "last_name": "Orban", "team_id": "43", "market_value": 31729385.0, "buy_price": 31923123.0, "user": "dsw", "player_id": "1246", "date": "2022-08-09T17:53:31+00:00", "position": "ABW", "trend": 1}, {"first_name": "Sheraldo", "last_name": "Becker", "team_id": "40", "market_value": 24122982.0, "buy_price": 22999999.0, "user": "dsw", "player_id": "2646", "date": "2022-08-23T13:09:43+00:00", "position": "ANG", "trend": 1}, {"first_name": "Theoson-Jordan", "last_name": "Siebatcheu Pefok", "team_id": "40", "market_value": 13177708.0, "buy_price": 25000009.0, "user": "dsw", "player_id": "3454", "date": "2022-08-30T07:36:15+00:00", "position": "ANG", "trend": 1}, {"first_name": "Kevin", "last_name": "Trapp", "team_id": "4", "market_value": 14955725.0, "buy_price": 13306612.0, "user": "dsw", "player_id": "429", "date": "2022-09-07T04:28:39+00:00", "position": "TW", "trend": 1}, {"first_name": "Diogo Filipe", "last_name": "Monteiro Pinto Leite", "team_id": "40", "market_value": 14821636.0, "buy_price": 18733123.0, "user": "dsw", "player_id": "4265", "date": "2022-09-26T00:32:57+00:00", "position": "ABW", "trend": 1}, {"first_name": "Micky", "last_name": "van de Ven", "team_id": "11", "market_value": 14721769.0, "buy_price": 10999999.0, "user": "dsw", "player_id": "3141", "date": "2022-11-02T14:50:01+00:00", "position": "ABW", "trend": 2}, {"first_name": "\u00c9ric", "last_name": "Ebimbe", "team_id": "4", "market_value": 4299358.0, "buy_price": 11111111.0, "user": "dsw", "player_id": "4406", "date": "2022-11-04T07:01:48+00:00", "position": "MF", "trend": 2}, {"first_name": "Jonjoe", "last_name": "Kenny", "team_id": "20", "market_value": 4184240.0, "buy_price": 12111111.0, "user": "dsw", "player_id": "2640", "date": "2022-11-22T22:50:19+00:00", "position": "ABW", "trend": 2}, {"first_name": "Gil", "last_name": "Basti\u00e3o Dias", "team_id": "9", "market_value": 5852187.0, "buy_price": 5111111.0, "user": "dsw", "player_id": "4627", "date": "2023-02-01T05:31:25+00:00", "position": "MF", "trend": 1}, {"first_name": "Rodrigo", "last_name": "Zalazar", "team_id": "8", "market_value": 5695509.0, "buy_price": 4444000.0, "user": "dsw", "player_id": "2680", "date": "2023-02-03T13:53:29+00:00", "position": "MF", "trend": 1}, {"first_name": "Silv\u00e8re", "last_name": "Ganvoula", "team_id": "24", "market_value": 500000.0, "buy_price": 500555.0, "user": "dsw", "player_id": "2469", "date": "2023-02-13T13:13:28+00:00", "position": "ANG", "trend": 0}, {"first_name": "Kevin", "last_name": "St\u00f6ger", "team_id": "24", "market_value": 8631160.0, "buy_price": 9452221.0, "user": "dsw", "player_id": "619", "date": "2023-02-14T12:52:58+00:00", "position": "MF", "trend": 2}, {"first_name": "Michael", "last_name": "Gregoritsch", "team_id": "5", "market_value": 26408091.0, "buy_price": 11767281.0, "user": "WhaTaDuDu", "player_id": "493", "date": "2022-08-03T17:14:03+00:00", "position": "ANG", "trend": 1}, {"first_name": "Vincenzo", "last_name": "Grifo", "team_id": "5", "market_value": 40505188.0, "buy_price": 42622000.0, "user": "WhaTaDuDu", "player_id": "118", "date": "2022-08-07T23:22:25+00:00", "position": "MF", "trend": 1}, {"first_name": "Karim", "last_name": "Adeyemi", "team_id": "3", "market_value": 21654981.0, "buy_price": 30222222.0, "user": "WhaTaDuDu", "player_id": "3482", "date": "2022-09-05T17:13:11+00:00", "position": "ANG", "trend": 1}, {"first_name": "Randal", "last_name": "Kolo Muani", "team_id": "4", "market_value": 32069644.0, "buy_price": 29444444.0, "user": "WhaTaDuDu", "player_id": "3480", "date": "2022-10-25T02:16:35+00:00", "position": "ANG", "trend": 1}, {"first_name": "Lukas", "last_name": "Hradecky", "team_id": "7", "market_value": 9397789.0, "buy_price": 10111111.0, "user": "WhaTaDuDu", "player_id": "1761", "date": "2022-11-06T21:24:36+00:00", "position": "TW", "trend": 2}, {"first_name": "Edmond", "last_name": "Tapsoba", "team_id": "7", "market_value": 16774979.0, "buy_price": 15777777.0, "user": "WhaTaDuDu", "player_id": "2783", "date": "2022-11-13T15:14:34+00:00", "position": "ABW", "trend": 1}, {"first_name": "Timo", "last_name": "Werner", "team_id": "43", "market_value": 27893478.0, "buy_price": 37888888.0, "user": "WhaTaDuDu", "player_id": "734", "date": "2022-11-22T17:40:36+00:00", "position": "ANG", "trend": 1}, {"first_name": "Julian", "last_name": "Ryerson", "team_id": "3", "market_value": 16866480.0, "buy_price": 35000000.0, "user": "WhaTaDuDu", "player_id": "2395", "date": "2023-01-26T01:03:09+00:00", "position": "ABW", "trend": 1}, {"first_name": "Anthony", "last_name": "Caci", "team_id": "18", "market_value": 8060205.0, "buy_price": 5588145.0, "user": "WhaTaDuDu", "player_id": "3470", "date": "2023-02-01T18:40:06+00:00", "position": "ABW", "trend": 1}, {"first_name": "Hiroki", "last_name": "Ito", "team_id": "9", "market_value": 11076236.0, "buy_price": 10915889.0, "user": "WhaTaDuDu", "player_id": "3089", "date": "2023-02-03T14:41:58+00:00", "position": "ABW", "trend": 2}, {"first_name": "Adam", "last_name": "Hlozek", "team_id": "7", "market_value": 10219103.0, "buy_price": 9580601.0, "user": "WhaTaDuDu", "player_id": "3471", "date": "2023-02-08T11:32:09+00:00", "position": "MF", "trend": 1}, {"first_name": "Rani", "last_name": "Khedira", "team_id": "40", "market_value": 10156290.0, "buy_price": 10666666.0, "user": "WhaTaDuDu", "player_id": "51", "date": "2023-02-11T22:27:40+00:00", "position": "MF", "trend": 1}, {"first_name": "Nicolas", "last_name": "H\u00f6fler", "team_id": "5", "market_value": 13573973.0, "buy_price": 14333333.0, "user": "WhaTaDuDu", "player_id": "581", "date": "2023-02-14T02:01:09+00:00", "position": "MF", "trend": 1}, {"first_name": "Daichi", "last_name": "Kamada", "team_id": "4", "market_value": 28419514.0, "buy_price": 15623521.0, "user": "Normy", "player_id": "2059", "date": "2022-08-20T03:11:50+00:00", "position": "MF", "trend": 1}, {"first_name": "Leroy", "last_name": "San\u00e9", "team_id": "2", "market_value": 42344457.0, "buy_price": 41700000.0, "user": "Normy", "player_id": "1222", "date": "2022-09-09T16:18:56+00:00", "position": "MF", "trend": 1}, {"first_name": "Yannick", "last_name": "Gerhardt", "team_id": "11", "market_value": 9605137.0, "buy_price": 1433552.0, "user": "Normy", "player_id": "1298", "date": "2022-09-03T21:11:37+00:00", "position": "MF", "trend": 2}, {"first_name": "Dayotchanculle", "last_name": "Upamecano", "team_id": "2", "market_value": 34655478.0, "buy_price": 36254145.0, "user": "Normy", "player_id": "1991", "date": "2022-10-03T02:57:23+00:00", "position": "ABW", "trend": 2}, {"first_name": "Ermedin", "last_name": "Demirovi\u0107", "team_id": "13", "market_value": 12504375.0, "buy_price": 13100000.0, "user": "Normy", "player_id": "2854", "date": "2022-10-12T16:51:12+00:00", "position": "ANG", "trend": 1}, {"first_name": "Manuel", "last_name": "Riemann", "team_id": "24", "market_value": 17787648.0, "buy_price": 15852562.0, "user": "Normy", "player_id": "1405", "date": "2022-10-18T07:45:57+00:00", "position": "TW", "trend": 1}, {"first_name": "David", "last_name": "Raum", "team_id": "43", "market_value": 18738746.0, "buy_price": 20400000.0, "user": "Normy", "player_id": "2522", "date": "2022-10-23T14:45:57+00:00", "position": "ABW", "trend": 2}, {"first_name": "Matthijs", "last_name": "de Ligt", "team_id": "2", "market_value": 32737245.0, "buy_price": 37258558.0, "user": "Normy", "player_id": "4286", "date": "2022-11-01T04:29:10+00:00", "position": "ABW", "trend": 1}, {"first_name": "Paulo", "last_name": "Ot\u00e1vio", "team_id": "11", "market_value": 20763892.0, "buy_price": 15121211.0, "user": "Normy", "player_id": "2447", "date": "2022-11-05T19:05:06+00:00", "position": "ABW", "trend": 1}, {"first_name": "Callum", "last_name": "Hudson-Odoi", "team_id": "7", "market_value": 4689322.0, "buy_price": 14215889.0, "user": "Normy", "player_id": "4417", "date": "2022-11-14T22:00:22+00:00", "position": "ANG", "trend": 2}, {"first_name": "Christoph", "last_name": "Baumgartner", "team_id": "14", "market_value": 17912259.0, "buy_price": 25232558.0, "user": "Normy", "player_id": "2275", "date": "2022-11-26T21:09:24+00:00", "position": "MF", "trend": 2}, {"first_name": "Mohamed", "last_name": "Simakan", "team_id": "43", "market_value": 19167432.0, "buy_price": 21152586.0, "user": "Normy", "player_id": "3001", "date": "2022-12-02T15:47:28+00:00", "position": "ABW", "trend": 1}, {"first_name": "Philipp", "last_name": "Hofmann", "team_id": "24", "market_value": 8982920.0, "buy_price": 6955555.0, "user": "Normy", "player_id": "46", "date": "2023-01-24T13:45:50+00:00", "position": "ANG", "trend": 1}, {"first_name": "Felix Kalu", "last_name": "Nmecha", "team_id": "11", "market_value": 11992791.0, "buy_price": 18525563.0, "user": "Normy", "player_id": "3069", "date": "2023-01-26T15:58:05+00:00", "position": "MF", "trend": 1}, {"first_name": "Alex", "last_name": "Kr\u00e1l", "team_id": "8", "market_value": 4197534.0, "buy_price": 3635525.0, "user": "Normy", "player_id": "4253", "date": "2023-02-16T10:27:30+00:00", "position": "MF", "trend": 1}, {"first_name": "Marvin", "last_name": "Ducksch", "team_id": "10", "market_value": 20088834.0, "buy_price": 20276763.0, "user": "Boonwin", "player_id": "82", "date": "2022-08-06T21:11:53+00:00", "position": "ANG", "trend": 1}, {"first_name": "Niclas", "last_name": "F\u00fcllkrug", "team_id": "10", "market_value": 30531739.0, "buy_price": 29500000.0, "user": "Boonwin", "player_id": "608", "date": "2022-10-25T17:16:22+00:00", "position": "ANG", "trend": 1}, {"first_name": "Matthias", "last_name": "Ginter", "team_id": "5", "market_value": 31534042.0, "buy_price": 30447395.0, "user": "Boonwin", "player_id": "49", "date": "2022-09-11T00:49:46+00:00", "position": "ABW", "trend": 1}, {"first_name": "Florian", "last_name": "Kainz", "team_id": "28", "market_value": 22343855.0, "buy_price": 24881867.0, "user": "Boonwin", "player_id": "1903", "date": "2022-10-21T05:10:20+00:00", "position": "MF", "trend": 1}, {"first_name": "Patrick", "last_name": "Wimmer", "team_id": "11", "market_value": 15510521.0, "buy_price": 8165566.0, "user": "Boonwin", "player_id": "3124", "date": "2022-10-31T12:38:08+00:00", "position": "MF", "trend": 2}, {"first_name": "Lucas", "last_name": "Silva Melo", "team_id": "4", "market_value": 13637032.0, "buy_price": 16272604.0, "user": "Boonwin", "player_id": "2378", "date": "2022-10-31T15:58:36+00:00", "position": "ABW", "trend": 2}, {"first_name": "Mathys", "last_name": "Tel", "team_id": "2", "market_value": 7013078.0, "buy_price": 14633189.0, "user": "Boonwin", "player_id": "4314", "date": "2022-11-11T07:04:54+00:00", "position": "ANG", "trend": 2}, {"first_name": "Ellyes", "last_name": "Skhiri", "team_id": "28", "market_value": 19128397.0, "buy_price": 14425854.0, "user": "Boonwin", "player_id": "2718", "date": "2022-11-16T23:16:59+00:00", "position": "MF", "trend": 1}, {"first_name": "Janis", "last_name": "Blaswich", "team_id": "43", "market_value": 9803004.0, "buy_price": 9999999.0, "user": "Boonwin", "player_id": "4", "date": "2022-12-12T10:34:50+00:00", "position": "TW", "trend": 2}, {"first_name": "Emre", "last_name": "Can", "team_id": "3", "market_value": 11540979.0, "buy_price": 3658439.0, "user": "Boonwin", "player_id": "54", "date": "2023-01-26T13:59:33+00:00", "position": "ABW", "trend": 1}, {"first_name": "Josip", "last_name": "Juranovic", "team_id": "40", "market_value": 11949959.0, "buy_price": 8883276.0, "user": "Boonwin", "player_id": "4598", "date": "2023-01-26T14:19:23+00:00", "position": "ABW", "trend": 2}, {"first_name": "Bartol", "last_name": "Franjic", "team_id": "11", "market_value": 500000.0, "buy_price": 501000.0, "user": "Boonwin", "player_id": "3476", "date": "2023-02-06T22:30:46+00:00", "position": "MF", "trend": 0}, {"first_name": "Benjamin", "last_name": "Henrichs", "team_id": "43", "market_value": 14103998.0, "buy_price": 12786130.0, "user": "Boonwin", "player_id": "1689", "date": "2023-02-09T08:29:04+00:00", "position": "ABW", "trend": 1}, {"first_name": "\u00d6rjan", "last_name": "Nyland", "team_id": "43", "market_value": 500000.0, "buy_price": 500000.0, "user": "Boonwin", "player_id": "1728", "date": "2023-02-10T03:27:18+00:00", "position": "TW", "trend": 0}, {"first_name": "Arijon", "last_name": "Ibrahimovi\u0107", "team_id": "2", "market_value": 1568362.0, "buy_price": 1276213.0, "user": "Boonwin", "player_id": "3176", "date": "2023-02-18T02:58:26+00:00", "position": "MF", "trend": 1}]